{
	"configurations" : 
	[
		{
			"directories" : 
			[
				{
					"build" : ".",
					"jsonFile" : "directory-.-Debug-f5ebdc15457944623624.json",
					"minimumCMakeVersion" : 
					{
						"string" : "3.17"
					},
					"projectIndex" : 0,
					"source" : ".",
					"targetIndexes" : 
					[
						0,
						1
					]
				}
			],
			"name" : "Debug",
			"projects" : 
			[
				{
					"directoryIndexes" : 
					[
						0
					],
					"name" : "Client",
					"targetIndexes" : 
					[
						0,
						1
					]
				}
			],
			"targets" : 
			[
				{
					"directoryIndex" : 0,
					"id" : "Client::@6890427a1f51a3e7e1df",
					"jsonFile" : "target-Client-Debug-b779b4dcd4c04eff0842.json",
					"name" : "Client",
					"projectIndex" : 0
				},
				{
					"directoryIndex" : 0,
					"id" : "SOURCE_FILES::@6890427a1f51a3e7e1df",
					"jsonFile" : "target-SOURCE_FILES-Debug-f9e47dc3a454d3379cb2.json",
					"name" : "SOURCE_FILES",
					"projectIndex" : 0
				}
			]
		}
	],
	"kind" : "codemodel",
	"paths" : 
	{
		"build" : "/home/canh2906/Music/caro_socket_c/Client/cmake-build-debug",
		"source" : "/home/canh2906/Music/caro_socket_c/Client"
	},
	"version" : 
	{
		"major" : 2,
		"minor" : 4
	}
}
